LICENSE
README.md
setup.py
kerasgen/__init__.py
kerasgen/balanced_image_dataset.py
kerasgen.egg-info/PKG-INFO
kerasgen.egg-info/SOURCES.txt
kerasgen.egg-info/dependency_links.txt
kerasgen.egg-info/requires.txt
kerasgen.egg-info/top_level.txt