Metadata-Version: 2.1
Name: kerasgen
Version: 0.1.2
Summary: A Keras/Tensorflow compatible image data generator for creating balanced batches
Home-page: https://github.com/ma7555/kerasgen
Author: Mahmoud Bahaa
Author-email: mah.alaa@nu.edu.eg
License: MIT
Platform: UNKNOWN
Classifier: Development Status :: 2 - Pre-Alpha
Classifier: License :: OSI Approved :: MIT License
Classifier: Programming Language :: Python :: 3
Classifier: Programming Language :: Python :: 3.7
Classifier: Programming Language :: Python :: 3.8
Classifier: Programming Language :: Python :: 3.9
Classifier: Programming Language :: Python :: 3.10
License-File: LICENSE
